opencensus/__init__.py
opencensus/ext/__init__.py
opencensus/ext/zenoss/__init__.py
opencensus/ext/zenoss/stats_exporter.py
opencensus_ext_zenoss-0.0.4.dist-info/LICENSE
opencensus_ext_zenoss-0.0.4.dist-info/METADATA
opencensus_ext_zenoss-0.0.4.dist-info/WHEEL
opencensus_ext_zenoss-0.0.4.dist-info/namespace_packages.txt
opencensus_ext_zenoss-0.0.4.dist-info/top_level.txt
opencensus_ext_zenoss-0.0.4.dist-info/RECORD
