Metadata-Version: 2.1
Name: opencensus-ext-zenoss
Version: 0.0.4
Summary: OpenCensus Zenoss Exporter
Home-page: https://github.com/zenoss/opencensus-python-exporter
Author: Zenoss, Inc.
Author-email: dev@zenoss.com
License: Apache-2.0
Platform: UNKNOWN
Classifier: Intended Audience :: Developers
Classifier: Development Status :: 3 - Alpha
Classifier: Intended Audience :: Developers
Classifier: License :: OSI Approved :: Apache Software License
Classifier: Programming Language :: Python
Classifier: Programming Language :: Python :: 2
Classifier: Programming Language :: Python :: 3
Requires-Python: >=2.7
Requires-Dist: google-cloud-monitoring (<1.0.0,>=0.30.0)
Requires-Dist: opencensus (<1.0.0,>=0.7)
Requires-Dist: requests
Requires-Dist: urllib3
